{
  "db_name": "PostgreSQL",
  "query": "CREATE TYPE DEPLOYMENT_STATUS AS ENUM( 'created', /* Created, but nothing pushed to it yet */ 'pushed', /* Something is pushed, but the system has not deployed it yet */ 'deploying', /* Something is pushed, and the system is currently deploying it */ 'running', /* Deployment is running successfully */ 'stopped', /* Deployment is stopped by the user */ 'errored', /* Deployment is stopped because of too many errors */ 'deleted' /* Deployment is deleted by the user */ );",
  "describe": {
    "columns": [],
    "parameters": {
      "Left": []
    },
    "nullable": []
  },
  "hash": "30653640dbfdeb1e2caa666a9b85be290220813278ce2acad9cc3590b7198d18"
}
